SimCodes/__init__.py
SimCodes/_version.py
SimCodes/ASTRA/Astra
SimCodes/ASTRA/Astra.exe
SimCodes/ASTRA/Astra.sh
SimCodes/ASTRA/Astra170919
SimCodes/ASTRA/Astra3.2
SimCodes/ASTRA/__init__.py
SimCodes/ASTRA/astra.sh
SimCodes/ASTRA/astra_MPICH2.sh
SimCodes/ASTRA/astra_MPICH2_Quiet.sh
SimCodes/ASTRA/astra_openmpi.sh
SimCodes/ASTRA/astra_r62M_Linux_x86_64_MPICH2_1.2.1
SimCodes/ASTRA/astra_r62M_Linux_x86_64_MPICH2_1.3.2p1
SimCodes/ASTRA/astra_r62_Linux_x86_64_OpenMPI_sld6
SimCodes/ASTRA/generator
SimCodes/ASTRA/generator.exe
SimCodes/ASTRA/generator.sh
SimCodes/ASTRA/libmpi_f90.so.1
SimCodes/ASTRA/lib/clog2TOdrawable.jar
SimCodes/ASTRA/lib/clog2TOslog2.jar
SimCodes/ASTRA/lib/clog2print.jar
SimCodes/ASTRA/lib/clogTOdrawable.jar
SimCodes/ASTRA/lib/clogTOslog2.jar
SimCodes/ASTRA/lib/clogprint.jar
SimCodes/ASTRA/lib/jumpshot.jar
SimCodes/ASTRA/lib/jumpshot_launcher.jar
SimCodes/ASTRA/lib/libampe.a
SimCodes/ASTRA/lib/libfmpich.a
SimCodes/ASTRA/lib/libfmpich.so
SimCodes/ASTRA/lib/libfmpich.so.2
SimCodes/ASTRA/lib/libfmpich.so.2.2
SimCodes/ASTRA/lib/liblmpe.a
SimCodes/ASTRA/lib/libmca_common_sm.la
SimCodes/ASTRA/lib/libmca_common_sm.so
SimCodes/ASTRA/lib/libmca_common_sm.so.2
SimCodes/ASTRA/lib/libmca_common_sm.so.2.0.0
SimCodes/ASTRA/lib/libmpe.a
SimCodes/ASTRA/lib/libmpe_collchk.a
SimCodes/ASTRA/lib/libmpe_f2cmpi.a
SimCodes/ASTRA/lib/libmpe_nompi.a
SimCodes/ASTRA/lib/libmpe_nompi_null.a
SimCodes/ASTRA/lib/libmpe_null.a
SimCodes/ASTRA/lib/libmpi.la
SimCodes/ASTRA/lib/libmpi.so
SimCodes/ASTRA/lib/libmpi.so.1
SimCodes/ASTRA/lib/libmpi.so.1.0.2
SimCodes/ASTRA/lib/libmpi_cxx.la
SimCodes/ASTRA/lib/libmpi_cxx.so
SimCodes/ASTRA/lib/libmpi_cxx.so.1
SimCodes/ASTRA/lib/libmpi_cxx.so.1.0.1
SimCodes/ASTRA/lib/libmpi_f77.la
SimCodes/ASTRA/lib/libmpi_f77.so
SimCodes/ASTRA/lib/libmpi_f77.so.1
SimCodes/ASTRA/lib/libmpi_f77.so.1.0.2
SimCodes/ASTRA/lib/libmpi_f90.la
SimCodes/ASTRA/lib/libmpi_f90.so
SimCodes/ASTRA/lib/libmpi_f90.so.1
SimCodes/ASTRA/lib/libmpi_f90.so.1.1.0
simcodes-1.0.3.dist-info/METADATA
simcodes-1.0.3.dist-info/WHEEL
simcodes-1.0.3.dist-info/top_level.txt
simcodes-1.0.3.dist-info/RECORD
