Metadata-Version: 2.4
Name: SimCodes
Version: 1.0.3
Summary: Simulation Codes for use with SimFrame.
Home-page: https://github.com/astec-stfc/simcodes
Author: James Jones
Author-email: James Jones <james.jones@stfc.ac.uk>
Maintainer-email: James Jones <james.jones@stfc.ac.uk>, Alex Brynes <alexander.brynes@stfc.ac.uk>
Project-URL: Homepage, https://github.com/astec-stfc/simcodes
Project-URL: Repository, https://github.com/astec-stfc/simcodes.git
Project-URL: Issues, https://github.com/astec-stfc/simcodes/-/issues/
Classifier: Programming Language :: Python :: 3.10
Requires-Python: >=3.10
Dynamic: author
Dynamic: home-page
Dynamic: requires-python
